[{"tags": ["javascript", "css", "audio", "synchronization"], "answers": [{"owner": {"user_id": 11887902, "display_name": "Mina"}, "answer_id": 78499307}, {"owner": {"user_id": 19508866, "display_name": "Rohit Bhati"}, "answer_id": 78499455}], "question_id": 78499192, "share_link": "https://stackoverflow.com/q/78499192", "title": "Sync CSS with Audio Loud Noise via Javascript"}, {"tags": ["php", "html", "web-scraping"], "answers": [{"owner": {"user_id": 2943403, "display_name": "mickmackusa"}, "answer_id": 78500304}], "question_id": 78499191, "share_link": "https://stackoverflow.com/q/78499191", "title": "Split text by &lt;br&gt; in PHP scraping result"}, {"tags": ["optimization", "cvxpy", "convex-optimization", "convex", "cvx"], "question_id": 78499190, "share_link": "https://stackoverflow.com/q/78499190", "title": "How to model log(e^x/(e^y+c)) in cvxpy with respect to DCP rules?"}, {"tags": ["sql", "mysql"], "answers": [{"owner": {"user_id": 20408114, "display_name": "Lishchuk Bohdan"}, "answer_id": 78499549}, {"owner": {"user_id": 25113670, "display_name": "AliJ"}, "answer_id": 78499329}], "question_id": 78499179, "share_link": "https://stackoverflow.com/q/78499179", "title": "How to use COUNT for multiple conditions?"}, {"tags": ["android", "adb", "device-admin", "device-policy-manager", "device-owner"], "question_id": 78499172, "share_link": "https://stackoverflow.com/q/78499172", "title": "Setting secure setting programmatically"}, {"tags": ["spring-boot", "gradle", "buildpack", "paketo"], "answers": [{"owner": {"user_id": 469679, "display_name": "Federico Nafria"}, "answer_id": 78500294}], "question_id": 78499170, "share_link": "https://stackoverflow.com/q/78499170", "title": "Spring Boot 404 when using &quot;pack build&quot; but it works when using &quot;./gradlew bootBuildImage&quot;"}, {"tags": ["node.js", "websocket", "trading", "quantitative-finance"], "question_id": 78499166, "share_link": "https://stackoverflow.com/q/78499166", "title": "Display Stock Tick data on react front end by calling websocket through a backend that calls the broker infrastructure"}, {"tags": ["kibana", "dql", "elk", "opensearch", "lucence"], "question_id": 78499165, "share_link": "https://stackoverflow.com/q/78499165", "title": "DQL wildcard get result in two direction"}, {"tags": ["python", "pandas", "dataframe"], "answers": [{"owner": {"user_id": 4497947, "display_name": "Parman M. Alizadeh"}, "answer_id": 78499290}, {"owner": {"user_id": 16343464, "display_name": "mozway"}, "answer_id": 78499180}, {"owner": {"user_id": 18470692, "display_name": "ouroboros1"}, "answer_id": 78499268}], "question_id": 78499163, "share_link": "https://stackoverflow.com/q/78499163", "title": "Why the difference in checking for value of pd.DataFrame vs pd.Series if value in index?"}, {"tags": ["javascript", "tizen", "tizen-web-app"], "answers": [{"owner": {"user_id": 25283088, "display_name": "webapi"}, "answer_id": 78542290}], "question_id": 78499161, "share_link": "https://stackoverflow.com/q/78499161", "title": "Volume OSD not visible on volume change using Tizen API"}, {"tags": ["javascript", "async-await", "promise", "event-loop"], "answers": [{"owner": {"user_id": 14098260, "display_name": "Alexander Nenashev"}, "answer_id": 78499251}], "question_id": 78499159, "share_link": "https://stackoverflow.com/q/78499159", "title": "Async/await promises alternative. Rewrite await to Promise"}, {"tags": ["python", "redis"], "answers": [{"owner": {"user_id": 14253459, "display_name": "Simone Di Cola"}, "answer_id": 78499573}], "question_id": 78499157, "share_link": "https://stackoverflow.com/q/78499157", "title": "Python connection timeouts to a Redis cluster"}, {"tags": ["vuejs3"], "answers": [{"owner": {"user_id": 23199816, "display_name": "TitoSenpai"}, "answer_id": 78499284}], "question_id": 78499154, "share_link": "https://stackoverflow.com/q/78499154", "title": "global directives: autofocus not working in Vuejs 3"}, {"tags": ["c#", "process", "processstartinfo", "yt-dlp"], "answers": [{"owner": {"user_id": 6697330, "display_name": "Boxbot"}, "answer_id": 78504585}], "question_id": 78499152, "share_link": "https://stackoverflow.com/q/78499152", "title": "Process execution from c# program having argument parsing error?"}, {"tags": ["reactjs", "react-hooks"], "question_id": 78499150, "share_link": "https://stackoverflow.com/q/78499150", "title": "React useCallback proper usage - improve performance or prevent stale reference?"}, {"tags": ["shopify", "blogs", "page-title"], "question_id": 78499149, "share_link": "https://stackoverflow.com/q/78499149", "title": "Shopify : Changing Page Title"}, {"tags": ["sql", "postgresql", "next.js", "vercel"], "question_id": 78499147, "share_link": "https://stackoverflow.com/q/78499147", "title": "Select objects by list id"}, {"tags": ["java", "android-studio"], "answers": [{"owner": {"user_id": 15316146, "display_name": "capcapbakkal"}, "answer_id": 78499186}], "question_id": 78499144, "share_link": "https://stackoverflow.com/q/78499144", "title": "Android Studio change button stroke"}, {"tags": ["reactjs", "redux", "redux-toolkit"], "answers": [{"owner": {"user_id": 2075944, "display_name": "phry"}, "answer_id": 78499682}, {"owner": {"user_id": 19857402, "display_name": "\u0414\u0430\u043d\u0438\u0438\u043b \u0412\u043b\u0430\u0434\u0438\u043c\u0438\u0440\u043e\u0432"}, "answer_id": 78507962}], "question_id": 78499140, "share_link": "https://stackoverflow.com/q/78499140", "title": "I constantly get the initial value from the reducer"}, {"tags": ["python", "methods", "overriding", "subclass", "cachetools"], "answers": [{"owner": {"user_id": 758174, "display_name": "Pierre D"}, "answer_id": 78500018}, {"owner": {"user_id": 10222217, "display_name": "HolderRoberts"}, "answer_id": 78499936}, {"owner": {"user_id": 24714692, "display_name": "user24714692"}, "answer_id": 78499938}], "question_id": 78499139, "share_link": "https://stackoverflow.com/q/78499139", "title": "Simulate an LFU cache"}, {"tags": ["c++", "templates"], "question_id": 78499131, "share_link": "https://stackoverflow.com/q/78499131", "title": "Template friend function in C++"}, {"tags": ["python", "visual-studio-code"], "answers": [{"owner": {"user_id": 8048915, "display_name": "Rodolfo N&#250;&#241;ez"}, "answer_id": 78499258}], "question_id": 78499130, "share_link": "https://stackoverflow.com/q/78499130", "title": "Visual Studio Code doesn&#39;t activate my virtual environment"}, {"tags": ["node.js", "amazon-rds", "amazon-aurora"], "question_id": 78499129, "share_link": "https://stackoverflow.com/q/78499129", "title": "Inconsistent reads after a write in MySQL Aurora"}, {"tags": ["python", "python-decorators"], "question_id": 78499128, "share_link": "https://stackoverflow.com/q/78499128", "title": "Return in Python Decorator"}, {"tags": ["flutter", "svg", "flutter-canvas"], "question_id": 78499127, "share_link": "https://stackoverflow.com/q/78499127", "title": "How to get the information necessary from a Widget&#39;s paint to convert to SVG"}, {"tags": ["reactjs", "node.js"], "question_id": 78499122, "share_link": "https://stackoverflow.com/q/78499122", "title": "Facing issue while routing and executing a build folder in nodejs"}, {"tags": ["laravel", "vue.js", "validation"], "question_id": 78499118, "share_link": "https://stackoverflow.com/q/78499118", "title": "Laravel Validation can not read required field"}, {"tags": ["python", "statistics", "random-forest", "p-value"], "answers": [{"owner": {"user_id": 6036253, "display_name": "Matt Haberland"}, "answer_id": 78502521}], "question_id": 78499117, "share_link": "https://stackoverflow.com/q/78499117", "title": "Methods to test independence in a non parametric setting"}, {"tags": ["css", "flutter", "figma"], "question_id": 78499114, "share_link": "https://stackoverflow.com/q/78499114", "title": "How to match a Shadow Figma design to a Flutter desing?"}, {"tags": ["android", "ionic-framework", "audio", "capacitor"], "question_id": 78499112, "share_link": "https://stackoverflow.com/q/78499112", "title": "Not able to playback audio file saved with capacitor-voice-recorder"}, {"tags": ["javascript", "jquery", "asp.net-mvc", "jquery-chosen"], "answers": [{"owner": {"user_id": 11887902, "display_name": "Mina"}, "answer_id": 78499208}, {"owner": {"user_id": 322084, "display_name": "chrwahl"}, "answer_id": 78499302}], "question_id": 78499111, "share_link": "https://stackoverflow.com/q/78499111", "title": "remove multiple attribute from chosen select jquery"}, {"tags": ["intellij-idea", "groovy", "spock"], "question_id": 78499105, "share_link": "https://stackoverflow.com/q/78499105", "title": "org.junit.platform.commons.JUnitException: TestEngine with ID &#39;spock&#39; failed to execute tests"}, {"tags": ["python", "modbus", "pymodbus"], "question_id": 78499101, "share_link": "https://stackoverflow.com/q/78499101", "title": "Modbus FC21 in pympdbus"}, {"tags": ["html", "css", "hover"], "answers": [{"owner": {"user_id": 7512028, "display_name": "fsdev"}, "answer_id": 78499133}], "question_id": 78499097, "share_link": "https://stackoverflow.com/q/78499097", "title": "I have an image link on my website that changes upon hovering my mouse over it, how do i turn both images into a link?"}, {"tags": ["cjk", "ascii-art"], "question_id": 78499096, "share_link": "https://stackoverflow.com/q/78499096", "title": "Image-to-Hanzi library"}, {"tags": ["webassembly", "ffmpeg-wasm"], "question_id": 78499093, "share_link": "https://stackoverflow.com/q/78499093", "title": "Stream data between main thread and webassembly worker thread in Browser"}, {"tags": ["supervisord"], "question_id": 78499091, "share_link": "https://stackoverflow.com/q/78499091", "title": "supervisor status is starting but running well"}, {"tags": ["javascript", "reactjs", "node.js", "next.js", "chat"], "question_id": 78499090, "share_link": "https://stackoverflow.com/q/78499090", "title": "Next.JS : Update URL without the page reloading"}, {"tags": ["amazon-web-services", "amazon-s3", "aws-lambda"], "question_id": 78499087, "share_link": "https://stackoverflow.com/q/78499087", "title": "How to trigger AWS Lambda when there&#39;s a malware detected in an S3 uploaded object using presigned url?"}, {"tags": ["c#", "asp.net-core", "asp.net-core-webapi", "action-filter"], "answers": [{"owner": {"user_id": 2501279, "display_name": "Guru Stron"}, "answer_id": 78499137}], "question_id": 78499086, "share_link": "https://stackoverflow.com/q/78499086", "title": "Getting an unknown Type at runtime in a Web API action filter"}, {"tags": ["c#", "linq", "reflection", "ienumerable", "linq2db"], "answers": [{"owner": {"user_id": 5133585, "display_name": "Sweeper"}, "answer_id": 78499138}, {"owner": {"user_id": 10646316, "display_name": "Svyatoslav Danyliv"}, "answer_id": 78503605}], "question_id": 78499085, "share_link": "https://stackoverflow.com/q/78499085", "title": "How to find IEnumerable&lt;T&gt;.ToList() method by explicitly specifying type of parameters and then call it with a custom parameter type?"}, {"tags": ["r", "windows", "terra"], "question_id": 78499080, "share_link": "https://stackoverflow.com/q/78499080", "title": "How do I solve the Zip file size problem with installing the terra package in R"}, {"tags": ["android", "networking", "network-programming"], "question_id": 78499079, "share_link": "https://stackoverflow.com/q/78499079", "title": "how to switch network programmatically in android"}, {"tags": ["f#", "fabulous"], "question_id": 78499078, "share_link": "https://stackoverflow.com/q/78499078", "title": "How to add key bindings to Fabulous View/Window?"}, {"tags": ["wordpress", "graphql", "nuxt.js", "apollo", "wp-graphql"], "question_id": 78499076, "share_link": "https://stackoverflow.com/q/78499076", "title": "GraphQL query on WordPress returns creation date instead of last modified date for posts"}, {"tags": ["python", "tensorflow", "deep-learning", "gpu", "artificial-intelligence"], "question_id": 78499075, "share_link": "https://stackoverflow.com/q/78499075", "title": "Installing TensorFlow with GPU Support: Compatibility and Setup Issues on Windows"}, {"tags": ["arduino", "aes", "lora", "cmac"], "answers": [{"owner": {"user_id": 25113554, "display_name": "Rain1603"}, "answer_id": 78538016}], "question_id": 78499074, "share_link": "https://stackoverflow.com/q/78499074", "title": "CMACLib function not running in Arduino loramesh sketch"}, {"tags": ["java", "amazon-s3", "sdk", "amazon-iam", "amazon-ecs"], "question_id": 78499073, "share_link": "https://stackoverflow.com/q/78499073", "title": "I am having issues accessing a an object in a bucket using S3 pre-signed URL. Can someone help on this?"}, {"tags": ["ios", "swift", "swiftui", "viewmodifier"], "answers": [{"owner": {"user_id": 5133585, "display_name": "Sweeper"}, "answer_id": 78499095}], "question_id": 78499072, "share_link": "https://stackoverflow.com/q/78499072", "title": "SwiftUI .onAppear and ViewModifier (Progress) procedure. Why it is important?"}, {"tags": ["spring-boot", "apache-camel", "activemq-artemis", "jta", "narayana"], "question_id": 78499071, "share_link": "https://stackoverflow.com/q/78499071", "title": "Apache Camel with ActiveMQ Artemis Cluster and JTA"}, {"tags": ["node.js", "express", "http", "http-delete", "http-patch"], "question_id": 78499068, "share_link": "https://stackoverflow.com/q/78499068", "title": "HTTP PATCH and DELETE requests not working in EJS project"}, {"tags": ["arduino", "serial-port", "arduino-ide"], "answers": [{"owner": {"user_id": 22951449, "display_name": "DOJ"}, "answer_id": 78510740}], "question_id": 78499062, "share_link": "https://stackoverflow.com/q/78499062", "title": "How to read information coming from RS232 on Arduino ATMEGA2560-PRO-CH340 on custom baud rate?"}, {"tags": ["swift", "core-data"], "question_id": 78499061, "share_link": "https://stackoverflow.com/q/78499061", "title": "How to store an array of a Core Data Entity by itself?"}, {"tags": ["c"], "question_id": 78499057, "share_link": "https://stackoverflow.com/q/78499057", "title": "How to change direction from (left to right) into (right to left)?"}, {"tags": ["php", "beanstalkd"], "answers": [{"owner": {"user_id": 6216, "display_name": "Alister Bulman"}, "answer_id": 78499658}], "question_id": 78499055, "share_link": "https://stackoverflow.com/q/78499055", "title": "How to access &quot;storage:ArrayObject:private&quot; property in Beanstalkd library Version 1.13+1+g91c54fc?"}, {"tags": ["elasticsearch"], "answers": [{"owner": {"user_id": 10685211, "display_name": "Musab Dogan"}, "answer_id": 78503879}], "question_id": 78499052, "share_link": "https://stackoverflow.com/q/78499052", "title": "Elastic Search distinct result"}, {"tags": ["typescript", "playwright", "playwright-test", "playwright-typescript"], "question_id": 78499050, "share_link": "https://stackoverflow.com/q/78499050", "title": "Not able to see context menu dialog on UI and trace mode (Playwright with Typescript)"}, {"tags": ["css", "visual-studio-code", "value-of-css-property"], "answers": [{"owner": {"user_id": 11107541, "display_name": "starball"}, "answer_id": 78504091}], "question_id": 78499046, "share_link": "https://stackoverflow.com/q/78499046", "title": "Why is VS Code is missing value suggestions for the CSS white-space property?"}, {"tags": ["python", "telegram", "telethon"], "question_id": 78499044, "share_link": "https://stackoverflow.com/q/78499044", "title": "AttributeError: module &#39;telethon.tl.functions.messages&#39; has no attribute &#39;GetAllChatsRequest&#39;"}, {"tags": ["mysql", "cicd"], "question_id": 78499039, "share_link": "https://stackoverflow.com/q/78499039", "title": "CI/CD can&#39;t connect to mariadb database"}, {"tags": ["android", "kotlin", "retrofit"], "question_id": 78499038, "share_link": "https://stackoverflow.com/q/78499038", "title": "OkHttpClient implementation security advice"}, {"tags": ["kubernetes-helm"], "answers": [{"owner": {"user_id": 10008173, "display_name": "David Maze"}, "answer_id": 78499515}], "question_id": 78499037, "share_link": "https://stackoverflow.com/q/78499037", "title": "How to use the condition field in dependencies with an array of objects in a helm chart with multiple subcharts"}, {"tags": ["python", "matplotlib"], "question_id": 78499036, "share_link": "https://stackoverflow.com/q/78499036", "title": "How to draw a large number of circles/spheres in matplotlib efficiently?"}, {"tags": ["php", "mysql", "wordpress", "xampp"], "answers": [{"owner": {"user_id": 3095702, "display_name": "foxfabi"}, "answer_id": 78499060}], "question_id": 78499035, "share_link": "https://stackoverflow.com/q/78499035", "title": "MySQL is rejecting connection when using WordPress in XAMPP"}, {"tags": ["javascript", "webpack", "frontend"], "question_id": 78499030, "share_link": "https://stackoverflow.com/q/78499030", "title": "In webpack-dev-server, how to custom dev server router to control webpack compiler instance"}, {"tags": ["android", "google-play-console"], "answers": [{"owner": {"user_id": 16930239, "display_name": "user16930239"}, "answer_id": 78505022}], "question_id": 78499029, "share_link": "https://stackoverflow.com/q/78499029", "title": "How to change my appbundle in Google Play Console?"}, {"tags": ["python"], "answers": [{"owner": {"user_id": 6451573, "display_name": "Jean-Fran&#231;ois Fabre"}, "answer_id": 78499040}, {"owner": {"user_id": 49849, "display_name": "user1686"}, "answer_id": 78499065}], "question_id": 78499028, "share_link": "https://stackoverflow.com/q/78499028", "title": "What does the tempfile.mkstemp(text=...) parameter actually do?"}, {"tags": ["apache-spark", "apache-spark-sql", "merge", "databricks", "delta"], "question_id": 78499027, "share_link": "https://stackoverflow.com/q/78499027", "title": "Delta Lake (OSS) merge operation never finishes (or takes too long)"}, {"tags": ["spring-boot", "nginx", "cloud"], "question_id": 78499023, "share_link": "https://stackoverflow.com/q/78499023", "title": "How to set up request overload protection?"}, {"tags": ["android", "kotlin", "android-jetpack-compose", "android-jetpack-compose-material3", "android-api-34"], "question_id": 78499021, "share_link": "https://stackoverflow.com/q/78499021", "title": "Material3 dynamic color not working in compose for Android API 34"}, {"tags": ["powershell"], "answers": [{"owner": {"user_id": 45375, "display_name": "mklement0"}, "answer_id": 78500643}, {"owner": {"user_id": 2518317, "display_name": "Hashbrown"}, "answer_id": 78500725}], "question_id": 78499020, "share_link": "https://stackoverflow.com/q/78499020", "title": "A way to tell the immediate runtime that invoked a `.ps1`"}, {"tags": ["python", "input"], "question_id": 78499019, "share_link": "https://stackoverflow.com/q/78499019", "title": "Allowing multiple user inputs"}, {"tags": ["javascript", "webpack", "frontend"], "question_id": 78499017, "share_link": "https://stackoverflow.com/q/78499017", "title": "Webpack 5 cannot update latest code when node_modules/mypkg is changed"}, {"tags": ["c++", "oop"], "question_id": 78499016, "share_link": "https://stackoverflow.com/q/78499016", "title": "Setting the type of a member variable in a base class based on a non-direct descendant?"}, {"tags": ["python", "jupyter-notebook", "pycharm", "jupyter"], "answers": [{"owner": {"user_id": 6696746, "display_name": "icaine"}, "answer_id": 78499043}], "question_id": 78499014, "share_link": "https://stackoverflow.com/q/78499014", "title": "How to collapse or better organize long Jupyter notebook cells in Pycharm IDE?"}, {"tags": ["mern"], "question_id": 78499012, "share_link": "https://stackoverflow.com/q/78499012", "title": "how to deploy a mern stack application on the github?"}, {"tags": ["java", "android", "kotlin"], "answers": [{"owner": {"user_id": 22887305, "display_name": "bhavy khanna"}, "answer_id": 78499054}], "question_id": 78499010, "share_link": "https://stackoverflow.com/q/78499010", "title": "Why can&#39;t I run a small Java program directly in Android Studio without converting it to Kotlin first?"}, {"tags": ["android", "tesseract"], "question_id": 78499009, "share_link": "https://stackoverflow.com/q/78499009", "title": "Tesseract - Tessdata folder cannot be found in Android"}, {"tags": ["python", "exception"], "question_id": 78499005, "share_link": "https://stackoverflow.com/q/78499005", "title": "How can I run a function/alert when Python script hit an error, like a ZeroDivisionError?"}, {"tags": ["kotlin", "android-jetpack-compose", "onbackpressed", "jetpack-compose-modalbottomsheet"], "answers": [{"owner": {"user_id": 11512499, "display_name": "Adnan Habib"}, "answer_id": 78500488}], "question_id": 78499004, "share_link": "https://stackoverflow.com/q/78499004", "title": "Handling Back Press during ModalBottomSheetLayout Animation in Jetpack Compose"}, {"tags": ["typescript"], "answers": [{"owner": {"user_id": 16505877, "display_name": "nidalovski"}, "answer_id": 78500780}], "question_id": 78499002, "share_link": "https://stackoverflow.com/q/78499002", "title": "No index signature with a parameter of type &#39;string&#39; was found on type &#39;Omit&lt;T, keyof T&gt;&#39;"}, {"tags": ["javascript", "reactjs", "react-hooks", "frontend"], "answers": [{"owner": {"user_id": 4331279, "display_name": "MWB"}, "answer_id": 78499042}, {"owner": {"user_id": 15007169, "display_name": "sina dadsetn"}, "answer_id": 78499067}, {"owner": {"user_id": 2232277, "display_name": "mcihak"}, "answer_id": 78499367}, {"owner": {"user_id": 13832116, "display_name": "\u064eAbolfazl agajanzadeh"}, "answer_id": 78499629}], "question_id": 78499001, "share_link": "https://stackoverflow.com/q/78499001", "title": "why useState doesn&#39;t work and how to fix it?"}, {"tags": ["c#", "entity-framework-core"], "question_id": 78498998, "share_link": "https://stackoverflow.com/q/78498998", "title": "Entity Framework Core 6 loop and change tracker"}, {"tags": ["grafana", "panel", "influxdb", "flux-influxdb"], "question_id": 78498990, "share_link": "https://stackoverflow.com/q/78498990", "title": "Trouble displaying annotations for tags in Grafana panel"}, {"tags": ["flutter", "flutter-sliver", "sliverappbar"], "answers": [{"owner": {"user_id": 23199816, "display_name": "TitoSenpai"}, "answer_id": 78499183}], "question_id": 78498989, "share_link": "https://stackoverflow.com/q/78498989", "title": "Flutter SliverAppBar clip flexibleSpace widget on scroll"}, {"tags": ["vba", "ms-word"], "answers": [{"owner": {"user_id": 22192445, "display_name": "taller"}, "answer_id": 78500384}], "question_id": 78498987, "share_link": "https://stackoverflow.com/q/78498987", "title": "Looping through a search using VBA in MS Word"}, {"tags": ["css", "vercel"], "answers": [{"owner": {"user_id": 2473909, "display_name": "DanieleAlessandra"}, "answer_id": 78499260}], "question_id": 78498985, "share_link": "https://stackoverflow.com/q/78498985", "title": "Why is vercel not rendering my css file while deploying in the web page?"}, {"tags": ["go", "tcpclient"], "question_id": 78498981, "share_link": "https://stackoverflow.com/q/78498981", "title": "A TCP client in Go - what to choose: conn.Write(data) or Fprintf(conn, data)?"}, {"tags": ["tailwind-css"], "answers": [{"owner": {"user_id": 19655631, "display_name": "Wongjn"}, "answer_id": 78499063}], "question_id": 78498980, "share_link": "https://stackoverflow.com/q/78498980", "title": "How to create striped background using tailwind?"}, {"tags": ["reactjs"], "answers": [{"owner": {"user_id": 10140124, "display_name": "Tushar Shahi"}, "answer_id": 78499197}], "question_id": 78498979, "share_link": "https://stackoverflow.com/q/78498979", "title": "Why is the state not updating in one case but do so in the other?"}, {"tags": ["python", "opencv", "drawing", "ellipse"], "answers": [{"owner": {"user_id": 4788546, "display_name": "CristiFati"}, "answer_id": 78500167}], "question_id": 78498976, "share_link": "https://stackoverflow.com/q/78498976", "title": "how to force cv2.ellipse to draw a clockwise circular arc?"}, {"tags": ["firebase", "google-cloud-run", "firebase-app-hosting"], "answers": [{"owner": {"user_id": 1298800, "display_name": "Thomas Bouldin"}, "answer_id": 78500097}], "question_id": 78498975, "share_link": "https://stackoverflow.com/q/78498975", "title": "How to provide different `runConfig` inside `apphosting.yaml` for different firebase project deployments?"}, {"tags": ["javascript", "reactjs", "file-upload", "material-ui", "card"], "question_id": 78498973, "share_link": "https://stackoverflow.com/q/78498973", "title": "I want to use a MUI Card to upload files in React"}, {"tags": ["python", "asynchronous"], "answers": [{"owner": {"user_id": 13944524, "display_name": "S.B"}, "answer_id": 78498986}], "question_id": 78498971, "share_link": "https://stackoverflow.com/q/78498971", "title": "Understanding Python Asynchronous Programming"}, {"tags": ["typescript", "vue.js", "vuejs3", "vue-component", "vue-composition-api"], "answers": [{"owner": {"user_id": 3731501, "display_name": "Estus Flask"}, "answer_id": 78499188}], "question_id": 78498967, "share_link": "https://stackoverflow.com/q/78498967", "title": "How to call the methods exposed by components in slots with Vue 3 Composition API"}, {"tags": ["python", "deep-learning", "classification"], "question_id": 78498963, "share_link": "https://stackoverflow.com/q/78498963", "title": "Output Classification prediction in KPConv"}, {"tags": ["c#", "unity-game-engine"], "question_id": 78498962, "share_link": "https://stackoverflow.com/q/78498962", "title": "Unity new input system triggering shoot multiple times"}, {"tags": ["python", "animation", "mediapipe"], "question_id": 78498961, "share_link": "https://stackoverflow.com/q/78498961", "title": "MediaPipe Landmarks to BVH"}, {"tags": ["java", "android", "xml", "gradle"], "question_id": 78498958, "share_link": "https://stackoverflow.com/q/78498958", "title": "Is there any way to invoke showInputMethodPicker() from TileService (onClick) without any Activity Opened"}, {"tags": ["json", "excel", "vba", "jsonparser", "vba6"], "question_id": 78498953, "share_link": "https://stackoverflow.com/q/78498953", "title": "VBA : Run-time error &#39;10001&#39; error parsing json"}]