[{"tags": ["powerbi"], "answers": [{"owner": {"user_id": 18965077, "display_name": "ttruhcheva"}, "answer_id": 78482589}], "question_id": 78480936, "share_link": "https://stackoverflow.com/q/78480936", "title": "Creating a separate table from existing table in PowerBI"}, {"tags": ["android", "gradle", "android-gradle-plugin", "aapt2"], "question_id": 78480930, "share_link": "https://stackoverflow.com/q/78480930", "title": "Android: How to configure stable resource id&#39;s with aapt2"}, {"tags": ["javascript", "html", "css", "ios", "safari"], "question_id": 78480926, "share_link": "https://stackoverflow.com/q/78480926", "title": "Safari prevents TR with display:none to be reshown using display:block or display:&#39;&#39;; UNLESS a JavaScript alert(&#39;&#39;) is used at the end"}, {"tags": ["mysql"], "answers": [{"owner": {"user_id": 17389, "display_name": "ysth"}, "answer_id": 78480952}, {"owner": {"user_id": 3229727, "display_name": "Eduardo Palacio"}, "answer_id": 78480953}, {"owner": {"user_id": 5193536, "display_name": "nbk"}, "answer_id": 78480958}], "question_id": 78480925, "share_link": "https://stackoverflow.com/q/78480925", "title": "Mysql Query For Multiple Categories"}, {"tags": ["azure", "azure-cognitive-search", "azure-ai-search"], "answers": [{"owner": {"user_id": 20237633, "display_name": "Sampath"}, "answer_id": 78483792}], "question_id": 78480923, "share_link": "https://stackoverflow.com/q/78480923", "title": "Using Index Projections to retrieve individual pages in Azure AI Search"}, {"tags": ["iframe", "refresh", "fancybox", "minicart"], "question_id": 78480922, "share_link": "https://stackoverflow.com/q/78480922", "title": "Refreshing minicart on parent page from within fancybox Iframe on HTML page. No woocommerce or wp"}, {"tags": ["assembly", "x86-64", "cpu-architecture", "intel"], "question_id": 78480921, "share_link": "https://stackoverflow.com/q/78480921", "title": "Why does the BSWAP x86-64 instruction have latency 2 on modern Intel processors?"}, {"tags": ["typescript"], "question_id": 78480918, "share_link": "https://stackoverflow.com/q/78480918", "title": "Does typescript have a way to infer a Map&#39;s value type based on the key?"}, {"tags": ["event-handling", "salesforce", "subscribe", "lwc", "aura-framework"], "question_id": 78480915, "share_link": "https://stackoverflow.com/q/78480915", "title": "Convert aura:handler to lightning web component"}, {"tags": ["java", "apache-kafka", "properties", "configuration", "micronaut"], "question_id": 78480911, "share_link": "https://stackoverflow.com/q/78480911", "title": "unable to feed property programmatically"}, {"tags": ["spring-boot", "spring-data-jpa", "spring-test"], "answers": [{"owner": {"user_id": 3728901, "display_name": "Vy Do"}, "answer_id": 78481565}], "question_id": 78480907, "share_link": "https://stackoverflow.com/q/78480907", "title": "Testing with spring boot, H2, Gradle not working"}, {"tags": ["google-sheets", "google-sheets-formula"], "answers": [{"owner": {"user_id": 5632629, "display_name": "player0"}, "answer_id": 78483080}, {"owner": {"user_id": 17887301, "display_name": "z.."}, "answer_id": 78480965}], "question_id": 78480902, "share_link": "https://stackoverflow.com/q/78480902", "title": "How can you make repetition on a sum equation faster?"}, {"tags": ["python", "pandas", "dataframe", "scipy", "scipy-optimize"], "answers": [{"owner": {"user_id": 313768, "display_name": "Reinderien"}, "answer_id": 78483466}, {"owner": {"user_id": 24714692, "display_name": "user24714692"}, "answer_id": 78480995}], "question_id": 78480901, "share_link": "https://stackoverflow.com/q/78480901", "title": "How to output x-value to given y-value of a previously fitted function?"}, {"tags": ["node.js", "github", "token", "github-api", "github-app"], "question_id": 78480893, "share_link": "https://stackoverflow.com/q/78480893", "title": "Transfer repositories between orgs using a Github App (and only its access token)"}, {"tags": ["python", "pycharm"], "answers": [{"owner": {"user_id": 25024368, "display_name": "Macxdmg"}, "answer_id": 78480937}], "question_id": 78480891, "share_link": "https://stackoverflow.com/q/78480891", "title": "pycharm - f string returns an icon"}, {"tags": ["c++", "ncurses", "tui"], "question_id": 78480889, "share_link": "https://stackoverflow.com/q/78480889", "title": "Inconsistency with mvwprintw in ncurses"}, {"tags": ["vba", "ms-word"], "answers": [{"owner": {"user_id": 22192445, "display_name": "taller"}, "answer_id": 78481090}], "question_id": 78480890, "share_link": "https://stackoverflow.com/q/78480890", "title": "Dependant radio buttons in Microsoft Word"}, {"tags": ["xslt", "xslt-1.0"], "answers": [{"owner": {"user_id": 252228, "display_name": "Martin Honnen"}, "answer_id": 78482783}], "question_id": 78480886, "share_link": "https://stackoverflow.com/q/78480886", "title": "Updating two different nodes using XSLT"}, {"tags": ["reactjs", "excel", "typescript", "xlsx", "sheetjs"], "question_id": 78480882, "share_link": "https://stackoverflow.com/q/78480882", "title": "Excel edit using Typescript"}, {"tags": ["ios", "xcode", "swiftui"], "answers": [{"owner": {"user_id": 5928873, "display_name": "alessionossa"}, "answer_id": 78480881}], "question_id": 78480880, "share_link": "https://stackoverflow.com/q/78480880", "title": "SwiftUI app View not filling the entire iPhone screen"}, {"tags": ["sql", "oracle"], "answers": [{"owner": {"user_id": 1509264, "display_name": "MT0"}, "answer_id": 78480897}], "question_id": 78480876, "share_link": "https://stackoverflow.com/q/78480876", "title": "Using multiple aggregations in a pivot in oracle"}, {"tags": ["typescript", "conditional-statements", "typeguards"], "answers": [{"owner": {"user_id": 62076, "display_name": "Alex Wayne"}, "answer_id": 78480927}], "question_id": 78480874, "share_link": "https://stackoverflow.com/q/78480874", "title": "Trying to add a typeguard dependent on content existing in the element in Typescript"}, {"tags": ["python", "dataframe", "function", "operators", "shift"], "answers": [{"owner": {"user_id": 2578235, "display_name": "Johnny Cheesecutter"}, "answer_id": 78480908}], "question_id": 78480872, "share_link": "https://stackoverflow.com/q/78480872", "title": "ComputeError with polars dataframe while trying to pass a column expressions in a simple shift() operation"}, {"tags": ["c#", "vb.net", "linq", "translate"], "answers": [{"owner": {"user_id": 284240, "display_name": "Tim Schmelter"}, "answer_id": 78480931}], "question_id": 78480871, "share_link": "https://stackoverflow.com/q/78480871", "title": "Converting C# LINQ query to VB"}, {"tags": ["java", "multithreading", "hashmap"], "answers": [{"owner": {"user_id": 139985, "display_name": "Stephen C"}, "answer_id": 78480961}, {"owner": {"user_id": 183406, "display_name": "meriton"}, "answer_id": 78481243}, {"owner": {"user_id": 768644, "display_name": "rzwitserloot"}, "answer_id": 78480968}, {"owner": {"user_id": 801894, "display_name": "Solomon Slow"}, "answer_id": 78481009}], "question_id": 78480869, "share_link": "https://stackoverflow.com/q/78480869", "title": "Understanding the inconsistent size of HashMap in a multithreaded Java program"}, {"tags": ["serial-port", "modem", "hyperterminal", "xmodem", "zmodem"], "answers": [{"owner": {"user_id": 1060650, "display_name": "Wisteso"}, "answer_id": 78486546}], "question_id": 78480868, "share_link": "https://stackoverflow.com/q/78480868", "title": "Extra mystery bytes with some XModem CRC transfers"}, {"tags": ["javascript", "html", "jquery", "internet-explorer", "iframe"], "question_id": 78480862, "share_link": "https://stackoverflow.com/q/78480862", "title": "document.write(htmlPage) throwing SCRIPT1002: Syntax Error in IE but works in Chrome and other browsers"}, {"tags": ["javascript", "firefox", "dom-events", "web-audio-api"], "answers": [{"owner": {"user_id": 3211046, "display_name": "chrisguttandin"}, "answer_id": 78522637}], "question_id": 78480859, "share_link": "https://stackoverflow.com/q/78480859", "title": "Firefox: arrow key does not count as user gesture, so cannt play AudioContext"}, {"tags": ["reactjs", "react-native"], "question_id": 78480858, "share_link": "https://stackoverflow.com/q/78480858", "title": "Wrap Two Text Elements in the same line when numberOfLines for one of the text elements is 2 - React Native"}, {"tags": ["sql", "sql-server", "t-sql", "sql-server-2012"], "answers": [{"owner": {"user_id": 13061224, "display_name": "siggemannen"}, "answer_id": 78482739}], "question_id": 78480852, "share_link": "https://stackoverflow.com/q/78480852", "title": "Take data from Lead Record when condition or filter criteria matches and ignore the records between current row and selected record (lead row)"}, {"tags": ["android", "android-studio", "material-design"], "answers": [{"owner": {"user_id": 14099625, "display_name": "djes"}, "answer_id": 78483025}], "question_id": 78480851, "share_link": "https://stackoverflow.com/q/78480851", "title": "Is there a style for disabled buttons in Android?"}, {"tags": ["php", "apache", "php-8", "php-8.2"], "question_id": 78480850, "share_link": "https://stackoverflow.com/q/78480850", "title": "PHP8 PHP-FPM how to exclude function args on www-error.log"}, {"tags": ["sql", "sql-server"], "answers": [{"owner": {"user_id": 4956336, "display_name": "p3consulting"}, "answer_id": 78485855}], "question_id": 78480848, "share_link": "https://stackoverflow.com/q/78480848", "title": "Randomize Occurrence Date by Series Id while keeping the order of dates"}, {"tags": ["arrays", "julia"], "answers": [{"owner": {"user_id": 10772985, "display_name": "xlxs4"}, "answer_id": 78485874}], "question_id": 78480847, "share_link": "https://stackoverflow.com/q/78480847", "title": "check if a view is contiguous in julia"}, {"tags": ["javascript", "reactjs", "if-statement"], "answers": [{"owner": {"user_id": 22157234, "display_name": "Dmitry"}, "answer_id": 78480914}, {"owner": {"user_id": 25047583, "display_name": "Abiodun"}, "answer_id": 78480935}], "question_id": 78480845, "share_link": "https://stackoverflow.com/q/78480845", "title": "How to know the trigger of an useEffect to make a conditional with it?"}, {"tags": ["statistics", "candlesticks"], "question_id": 78480841, "share_link": "https://stackoverflow.com/q/78480841", "title": "Fitted Line (through midpoints of 30 min candle sticks)"}, {"tags": ["asynchronous", "rust", "rust-tokio", "worker-thread", "rust-tonic"], "question_id": 78480839, "share_link": "https://stackoverflow.com/q/78480839", "title": "Using server-side streaming RPC in tonic, is it safe to do heavy compute without spawn_blocking?"}, {"tags": ["java", "android"], "answers": [{"owner": {"user_id": 22887305, "display_name": "bhavy khanna"}, "answer_id": 78489318}], "question_id": 78480837, "share_link": "https://stackoverflow.com/q/78480837", "title": "Android Studio closes my project when minimizing the window or building/running the project"}, {"tags": ["javascript", "three.js", "3d", "geometry"], "answers": [{"owner": {"user_id": 2336212, "display_name": "shieldgenerator7"}, "answer_id": 78514268}, {"owner": {"user_id": 19093908, "display_name": "\u0141ukasz D. Mastalerz"}, "answer_id": 78485870}], "question_id": 78480836, "share_link": "https://stackoverflow.com/q/78480836", "title": "How to make a Prismoid in Three.js?"}, {"tags": ["reactjs", "google-cloud-platform", "single-page-application", "identity-aware-proxy"], "question_id": 78480835, "share_link": "https://stackoverflow.com/q/78480835", "title": "Authenticate GCP client library from SPA via the IAP credentials"}, {"tags": ["keycloak", "openid-connect"], "question_id": 78480831, "share_link": "https://stackoverflow.com/q/78480831", "title": "Logout from all Keycloak clients"}, {"tags": ["ipados"], "question_id": 78480829, "share_link": "https://stackoverflow.com/q/78480829", "title": "Use Presenter View on iPad when mirroring to another monitor"}, {"tags": ["angular", "asynchronous", "jestjs", "ts-jest", "migrating"], "answers": [{"owner": {"user_id": 21644695, "display_name": "IMeyers20"}, "answer_id": 78491799}], "question_id": 78480820, "share_link": "https://stackoverflow.com/q/78480820", "title": "Angular 17 fakeAsync tasks not running until test is cleaned up with &#39;resetFakeAsyncZone()&#39;"}, {"tags": ["paypal", "paypal-sandbox"], "answers": [{"owner": {"user_id": 2069605, "display_name": "Preston PHX"}, "answer_id": 78480857}], "question_id": 78480817, "share_link": "https://stackoverflow.com/q/78480817", "title": "PayPal JS SDK buttons and Orders API: How to set the billing address country?"}, {"tags": ["solr"], "question_id": 78480816, "share_link": "https://stackoverflow.com/q/78480816", "title": "Number searches in Solr returning decimals"}, {"tags": ["python", "python-3.x", "sockets"], "question_id": 78480812, "share_link": "https://stackoverflow.com/q/78480812", "title": "How can I run python code, inside an active program with the reference to the scope of the given program?"}, {"tags": ["reactjs", "asp.net-core", "authentication", "asp.net-identity"], "question_id": 78480810, "share_link": "https://stackoverflow.com/q/78480810", "title": "Error while getting current logged in user Asp .NET Core Web API + ReactJs"}, {"tags": ["wordpress", "woocommerce", "components", "cart", "gutenberg-blocks"], "question_id": 78480809, "share_link": "https://stackoverflow.com/q/78480809", "title": "Modify cart item subtotal format in the WooCommerce cart block"}, {"tags": ["flutter", "xcode", "macos"], "answers": [{"owner": {"user_id": 5191510, "display_name": "Lance Peterson"}, "answer_id": 78498166}], "question_id": 78480806, "share_link": "https://stackoverflow.com/q/78480806", "title": "Flutter: setting macos deployment version in XCode doesn&#39;t work"}, {"tags": ["powershell"], "question_id": 78480802, "share_link": "https://stackoverflow.com/q/78480802", "title": "Powershell can&#39;t kill process, saying &quot;There are no running instance of the task&quot; but Task Manager or WMIC can kill process. Why?"}, {"tags": ["c#", ".net", "asp.net-core-testhost"], "question_id": 78480800, "share_link": "https://stackoverflow.com/q/78480800", "title": "ConfigureTestServices executes in unexpected order"}, {"tags": ["pandas", "dataframe"], "answers": [{"owner": {"user_id": 9473764, "display_name": "Nick"}, "answer_id": 78481035}, {"owner": {"user_id": 11850322, "display_name": "PTQuoc"}, "answer_id": 78480834}, {"owner": {"user_id": 16343464, "display_name": "mozway"}, "answer_id": 78481517}], "question_id": 78480795, "share_link": "https://stackoverflow.com/q/78480795", "title": "Pandas Remove First Character From Column if Conditions Are Met"}, {"tags": ["javascript", "reactjs", "typescript", "next.js", "leaflet"], "answers": [{"owner": {"user_id": 4864063, "display_name": "jmcgriz"}, "answer_id": 78485570}], "question_id": 78480793, "share_link": "https://stackoverflow.com/q/78480793", "title": "Hide rest of map around country with leaflet.js in next js"}, {"tags": ["sql", "recursive-query"], "answers": [{"owner": {"user_id": 6354775, "display_name": "Abhinav Singh"}, "answer_id": 78485501}], "question_id": 78480792, "share_link": "https://stackoverflow.com/q/78480792", "title": "For each employee need to get the sum of values based on their start date every month"}, {"tags": ["excel", "vba"], "answers": [{"owner": {"user_id": 22192445, "display_name": "taller"}, "answer_id": 78481003}], "question_id": 78480791, "share_link": "https://stackoverflow.com/q/78480791", "title": "Transfer of document"}, {"tags": ["c#", "generics", "game-development", "godot", "godot4"], "answers": [{"owner": {"user_id": 21695189, "display_name": "MeSteve95"}, "answer_id": 78520179}], "question_id": 78480785, "share_link": "https://stackoverflow.com/q/78480785", "title": "Godot C# - Use Generic Type as Signal Parameter"}, {"tags": ["azure", "function"], "answers": [{"owner": {"user_id": 21742096, "display_name": "Ikhtesam Afrin"}, "answer_id": 78481659}], "question_id": 78480784, "share_link": "https://stackoverflow.com/q/78480784", "title": "API call sequence or priority c#"}, {"tags": ["multithreading", "rust", "vector"], "question_id": 78480783, "share_link": "https://stackoverflow.com/q/78480783", "title": "Problem with creating multiple threads to operate on different parts of vec"}, {"tags": ["npm", "canvas", "highcharts", "uglifyjs"], "answers": [{"owner": {"user_id": 4488333, "display_name": "Marcin Zareba"}, "answer_id": 78503074}], "question_id": 78480781, "share_link": "https://stackoverflow.com/q/78480781", "title": "Dependencies breaking npm build presumably bringing ES6 code into ES5 compatible legacy build"}, {"tags": ["bash"], "answers": [{"owner": {"user_id": 807037, "display_name": "Noel Yap"}, "answer_id": 78480782}, {"owner": {"user_id": 14122, "display_name": "Charles Duffy"}, "answer_id": 78480805}], "question_id": 78480780, "share_link": "https://stackoverflow.com/q/78480780", "title": "How to search and replace bash variable with braces?"}, {"tags": ["python", "dictionary", "nested"], "answers": [{"owner": {"user_id": 24714692, "display_name": "user24714692"}, "answer_id": 78480789}, {"owner": {"user_id": 10035985, "display_name": "Andrej Kesely"}, "answer_id": 78480825}, {"owner": {"user_id": 15261315, "display_name": "Chris"}, "answer_id": 78487739}], "question_id": 78480775, "share_link": "https://stackoverflow.com/q/78480775", "title": "Recursively replacing or updating key value pairs in a nested dictionary"}, {"tags": ["web-scraping"], "answers": [{"owner": {"user_id": 8922289, "display_name": "Ezequiel Fajreldines Dos Santo"}, "answer_id": 78481525}], "question_id": 78480770, "share_link": "https://stackoverflow.com/q/78480770", "title": "Web scraping Newegg with Python"}, {"tags": ["linux", "rstudio"], "question_id": 78480771, "share_link": "https://stackoverflow.com/q/78480771", "title": "How to increase the memory size limit for Rstudio in Linux?"}, {"tags": ["java", "jfilechooser"], "answers": [{"owner": {"user_id": 4679320, "display_name": "prasad_"}, "answer_id": 78481721}, {"owner": {"user_id": 2164365, "display_name": "Abra"}, "answer_id": 78482888}, {"owner": {"user_id": 131872, "display_name": "camickr"}, "answer_id": 78485588}, {"owner": {"user_id": 5399598, "display_name": "CoSoCo"}, "answer_id": 78503979}], "question_id": 78480769, "share_link": "https://stackoverflow.com/q/78480769", "title": "{How to toggle the current directory in `JFileChooser`?"}, {"tags": ["python", "python-2.7", "ssl-certificate", "centos7"], "question_id": 78480768, "share_link": "https://stackoverflow.com/q/78480768", "title": "Problem with python server cert? - &quot;There was a problem confirming the ssl certificate: [SSL: CERTIFICATE_VERIFY_FAILED] certificate verify failed.&quot;"}, {"tags": ["python", "elasticsearch"], "answers": [{"owner": {"user_id": 17698538, "display_name": "randomDev"}, "answer_id": 78488121}], "question_id": 78480767, "share_link": "https://stackoverflow.com/q/78480767", "title": "Elastic Search fields and values statistics?"}, {"tags": ["node.js", "windows", "tunnel", "tunneling", "localtunnel"], "answers": [{"owner": {"user_id": 22269187, "display_name": "jam j"}, "answer_id": 78480870}], "question_id": 78480765, "share_link": "https://stackoverflow.com/q/78480765", "title": "Tunnel Mole not giving urls"}, {"tags": ["php", "html", "regex", "preg-match-all"], "question_id": 78480764, "share_link": "https://stackoverflow.com/q/78480764", "title": "How can I use preg_match_all to get text not wrapped in html and store in array"}, {"tags": ["docker", "guacamole"], "answers": [{"owner": {"user_id": 1815577, "display_name": "datawookie"}, "answer_id": 78483091}], "question_id": 78480763, "share_link": "https://stackoverflow.com/q/78480763", "title": "Guacamole Docker version - must login to mySQL to work"}, {"tags": ["java", "sockets", "serversocket", "objectinputstream", "objectoutputstream"], "question_id": 78480752, "share_link": "https://stackoverflow.com/q/78480752", "title": "Continuous Socket connection, ObjectInputStream EOF on second request"}, {"tags": ["bash", "git", "version-control", "local", "remote-server"], "question_id": 78480751, "share_link": "https://stackoverflow.com/q/78480751", "title": "How to pull from a remote repo to a local repo, when the local repo is not empty?"}, {"tags": ["flutter", "dart", "currency-formatting"], "answers": [{"owner": {"user_id": 13973724, "display_name": "Harsh Sureja"}, "answer_id": 78481679}], "question_id": 78480750, "share_link": "https://stackoverflow.com/q/78480750", "title": "Flutter format currency from Currency Code"}, {"tags": ["python", "postgresql", "flask", "sqlalchemy"], "question_id": 78480745, "share_link": "https://stackoverflow.com/q/78480745", "title": "sqlalchemy.exc.CompileError: PostgreSQL ENUM type requires a name"}, {"tags": ["mongodb", "mongodb-query", "aggregation-framework", "profiler"], "question_id": 78480736, "share_link": "https://stackoverflow.com/q/78480736", "title": "What elements should I consider to determine efficiency with the MongoDB profiler?"}, {"tags": ["javascript", "reactjs", "next.js"], "answers": [{"owner": {"user_id": 22881124, "display_name": "Michael Walker"}, "answer_id": 78480804}], "question_id": 78480731, "share_link": "https://stackoverflow.com/q/78480731", "title": "Next.js useDebouncedCallback does not seem to delay the request"}, {"tags": ["azure-devops", "yaml", "azure-pipelines", "azure-pipelines-yaml"], "answers": [{"owner": {"user_id": 14697693, "display_name": "Bright Ran-MSFT"}, "answer_id": 78487406}], "question_id": 78480729, "share_link": "https://stackoverflow.com/q/78480729", "title": "Pipeline fails when adding multiple resources in YAML file"}, {"tags": ["html", "ajax", "iframe", "x-frame-options"], "question_id": 78480728, "share_link": "https://stackoverflow.com/q/78480728", "title": "How to run X-frame-option deny/sameorigin on a website (Iframe)"}, {"tags": ["oauth-2.0"], "question_id": 78480725, "share_link": "https://stackoverflow.com/q/78480725", "title": "How can we create our own Oauth server"}, {"tags": ["python", "datetime", "extract", "hour"], "answers": [{"owner": {"user_id": 23165407, "display_name": "Argetlam"}, "answer_id": 78480739}, {"owner": {"user_id": 511571, "display_name": "Virtually Real"}, "answer_id": 78480748}], "question_id": 78480724, "share_link": "https://stackoverflow.com/q/78480724", "title": "TypeError: &#39;int&#39; object is not callable for datetime"}, {"tags": ["dynamics-crm", "powerapps", "dataverse", "powerapps-modeldriven"], "answers": [{"owner": {"user_id": 8482390, "display_name": "ray gan"}, "answer_id": 78505684}], "question_id": 78480723, "share_link": "https://stackoverflow.com/q/78480723", "title": "Is it possible to do dynamic filter in dataverse table view?"}, {"tags": ["c#", "entity-framework-core", "blazor"], "question_id": 78480719, "share_link": "https://stackoverflow.com/q/78480719", "title": "Where can I find Components_Pages_pagename_razor.g.cs?"}, {"tags": ["dynamics-business-central", "dynamics-al", "businesscentral"], "answers": [{"owner": {"user_id": 913935, "display_name": "kaspermoerch"}, "answer_id": 78482044}], "question_id": 78480718, "share_link": "https://stackoverflow.com/q/78480718", "title": "Get Marketing Text with Business Central Dynamics AL"}, {"tags": ["sql", "sql-server", "t-sql"], "question_id": 78480714, "share_link": "https://stackoverflow.com/q/78480714", "title": "How to select 5 row columns into new columns"}, {"tags": ["excel", "vba", "sharepoint"], "answers": [{"owner": {"user_id": 478884, "display_name": "Tim Williams"}, "answer_id": 78480776}], "question_id": 78480712, "share_link": "https://stackoverflow.com/q/78480712", "title": "Saving Excel file to Sharepoint failing"}, {"tags": ["c#", "sql-server", "testcontainers"], "question_id": 78480703, "share_link": "https://stackoverflow.com/q/78480703", "title": "Execute insert query in TestContainers C#"}, {"tags": ["flutter", "release", "freeze", "device"], "question_id": 78480699, "share_link": "https://stackoverflow.com/q/78480699", "title": "Flutter release build stuck"}, {"tags": ["react-native", "crashlytics", "fatal-error", "react-native-hermes"], "question_id": 78480697, "share_link": "https://stackoverflow.com/q/78480697", "title": "Couldn&#39;t find DSO to load: libhermes.so SoSource"}, {"tags": ["python", "numpy", "class", "object", "operators"], "question_id": 78480694, "share_link": "https://stackoverflow.com/q/78480694", "title": "How do I define a custom method for @ operator?"}, {"tags": ["machine-learning"], "question_id": 78480688, "share_link": "https://stackoverflow.com/q/78480688", "title": "&quot;PLS-00201: identifier &#39;SYS.RQSCRIPTCREATE&#39; must be declared&quot; error when creating an embedded R script in oml4r"}, {"tags": ["google-sheets", "google-apps-script", "chatbot", "zendesk", "zendesk-api"], "question_id": 78480687, "share_link": "https://stackoverflow.com/q/78480687", "title": "How to make an API call for Zendesk Chatbot using Googlesheets as a database"}, {"tags": ["javascript", "html", "jquery", "gridview", "datatable"], "answers": [{"owner": {"user_id": 1491895, "display_name": "Barmar"}, "answer_id": 78480759}], "question_id": 78480683, "share_link": "https://stackoverflow.com/q/78480683", "title": "How to pass list of LICN_CIVIL_ID that have checkbox checked true separated comma using java script?"}, {"tags": ["node.js", "puppeteer"], "question_id": 78480682, "share_link": "https://stackoverflow.com/q/78480682", "title": "Puppeteer - Symbol.dispose ??= Symbol(&#39;dispose&#39;);"}, {"tags": ["javascript", "playwright"], "question_id": 78480680, "share_link": "https://stackoverflow.com/q/78480680", "title": "addLocatorHandler() does not seem to work with iframes"}, {"tags": ["python", "numpy", "setuptools", "distutils", "python-3.12"], "question_id": 78480676, "share_link": "https://stackoverflow.com/q/78480676", "title": "Migration from numpy.distutils"}, {"tags": ["java", "nio"], "answers": [{"owner": {"user_id": 6535366, "display_name": "JimN"}, "answer_id": 78481039}, {"owner": {"user_id": 420096, "display_name": "Sombriks"}, "answer_id": 78481052}], "question_id": 78480674, "share_link": "https://stackoverflow.com/q/78480674", "title": "Java NIO server-client - Connection refused"}, {"tags": ["python", "list", "multidimensional-array"], "answers": [{"owner": {"user_id": 24714692, "display_name": "user24714692"}, "answer_id": 78480706}, {"owner": {"user_id": 3058609, "display_name": "Adam Smith"}, "answer_id": 78480720}, {"owner": {"user_id": 18145660, "display_name": "Michael Chen"}, "answer_id": 78480753}, {"owner": {"user_id": 12730670, "display_name": "Tokay"}, "answer_id": 78480778}], "question_id": 78480671, "share_link": "https://stackoverflow.com/q/78480671", "title": "How to calculate total sum of all the elements present in the list. The elements in the list can be integers or nested lists"}, {"tags": ["google-sheets"], "answers": [{"owner": {"user_id": 13045193, "display_name": "doubleunary"}, "answer_id": 78480721}, {"owner": {"user_id": 9978746, "display_name": "E.Wiest"}, "answer_id": 78480788}], "question_id": 78480670, "share_link": "https://stackoverflow.com/q/78480670", "title": "Rolling 12 week average calculation"}, {"tags": ["java", "mockito", "powermock", "powermockito"], "answers": [{"owner": {"user_id": 9610415, "display_name": "TechGoose"}, "answer_id": 78491511}], "question_id": 78480669, "share_link": "https://stackoverflow.com/q/78480669", "title": "Power Mock and Mockito Version Incompatible"}, {"tags": ["db2"], "answers": [{"owner": {"user_id": 15820236, "display_name": "ethanjscott"}, "answer_id": 78557133}], "question_id": 78480666, "share_link": "https://stackoverflow.com/q/78480666", "title": "Get last part of the path with IFS_OBJECT_STATISTICS?"}, {"tags": ["java", "spring", "spring-data-jpa", "spring-data"], "answers": [{"owner": {"user_id": 2743585, "display_name": "wi2ard"}, "answer_id": 78483523}], "question_id": 78480663, "share_link": "https://stackoverflow.com/q/78480663", "title": "Can&#39;t delete entity with EmbeddableId in Spring JPA"}]